aliyunsdkitag/__init__.py
aliyunsdkitag/endpoint.py
aliyunsdkitag/request/__init__.py
aliyunsdkitag/request/v20210517/AbandonItemByAdminRequest.py
aliyunsdkitag/request/v20210517/AbandonItemRequest.py
aliyunsdkitag/request/v20210517/AcceptSamplingTaskRequest.py
aliyunsdkitag/request/v20210517/AddMemberOrGroupTaskRequest.py
aliyunsdkitag/request/v20210517/AddUserRequest.py
aliyunsdkitag/request/v20210517/AddUserToGroupRequest.py
aliyunsdkitag/request/v20210517/AddUserToTntRequest.py
aliyunsdkitag/request/v20210517/AppendDataToDatasetRequest.py
aliyunsdkitag/request/v20210517/AsyncDownloadMarkResultRequest.py
aliyunsdkitag/request/v20210517/BatchRejectTaskRequest.py
aliyunsdkitag/request/v20210517/CanCommitRequest.py
aliyunsdkitag/request/v20210517/CheckModelRequest.py
aliyunsdkitag/request/v20210517/CommitSubTaskRequest.py
aliyunsdkitag/request/v20210517/CreateDatasetRequest.py
aliyunsdkitag/request/v20210517/CreateModelRequest.py
aliyunsdkitag/request/v20210517/CreateOptionTemplateRequest.py
aliyunsdkitag/request/v20210517/CreateOrUpdateTntConfigRequest.py
aliyunsdkitag/request/v20210517/CreateTaskRequest.py
aliyunsdkitag/request/v20210517/CreateUserGroupRequest.py
aliyunsdkitag/request/v20210517/DeleteFeedbackRequest.py
aliyunsdkitag/request/v20210517/DeleteModelRequest.py
aliyunsdkitag/request/v20210517/DeleteOptionTemplateRequest.py
aliyunsdkitag/request/v20210517/DeleteTaskRequest.py
aliyunsdkitag/request/v20210517/DeleteUserGroupRequest.py
aliyunsdkitag/request/v20210517/DiscardSubTaskRequest.py
aliyunsdkitag/request/v20210517/DownloadIntPersonSummaryRequest.py
aliyunsdkitag/request/v20210517/ExportOptionTemplateRequest.py
aliyunsdkitag/request/v20210517/ExtendUserAuthInTaskRequest.py
aliyunsdkitag/request/v20210517/FetchVideoMarkResultRequest.py
aliyunsdkitag/request/v20210517/FlowInstanceCallbackRequest.py
aliyunsdkitag/request/v20210517/GetAssignedCheckTaskSummaryRequest.py
aliyunsdkitag/request/v20210517/GetBizPersonSummaryRequest.py
aliyun_python_sdk_itag-1.0.0.dist-info/LICENSE
aliyun_python_sdk_itag-1.0.0.dist-info/METADATA
aliyun_python_sdk_itag-1.0.0.dist-info/WHEEL
aliyun_python_sdk_itag-1.0.0.dist-info/top_level.txt
aliyun_python_sdk_itag-1.0.0.dist-info/RECORD
